README.rst
_description.org
lh-agpl3-LICENSE.txt
pyproject.toml
setup.py
bin/usgAcctAdmin.cs
bisos/__init__.py
bisos.usgAcct.egg-info/PKG-INFO
bisos.usgAcct.egg-info/SOURCES.txt
bisos.usgAcct.egg-info/dependency_links.txt
bisos.usgAcct.egg-info/not-zip-safe
bisos.usgAcct.egg-info/requires.txt
bisos.usgAcct.egg-info/top_level.txt
bisos/usgAcct/__init__.py
bisos/usgAcct/usgAcct.py
bisos/usgAcct/usgAcctPkgThis.py